{
  "name": "Abyssal",
  "tree": {
    "$className": "DataModel",
    "ReplicatedStorage": {
      "$className": "ReplicatedStorage",
      "Modules": { "$path": "src/ReplicatedStorage/Modules" },
      "Remotes": { "$path": "src/ReplicatedStorage/Remotes" },
      "LightingSystem": { "$path": "src/ReplicatedStorage/LightingSystem" },
      "SwimmingSystem": { "$path": "src/ReplicatedStorage/SwimmingSystem" }
    },
    "ServerScriptService": {
      "$className": "ServerScriptService",
      "Config": { "$path": "src/ServerScriptService/Config" },
      "Systems": { "$path": "src/ServerScriptService/Systems" },
      "Security": { "$path": "src/ServerScriptService/Security" },
      "SwimmingSystem": { "$path": "src/ServerScriptService/SwimmingSystem" },
      "WaterFloatService": { "$path": "src/ServerScriptService/WaterFloatService.server.lua" }
    },
    "StarterPlayer": {
      "$className": "StarterPlayer",
      "StarterPlayerScripts": {
        "$className": "StarterPlayerScripts",
        "$path": "src/StarterPlayer/StarterPlayerScripts"
      }
    },
    "StarterGui": {
      "$className": "StarterGui",
      "SubmarineControlGUI": { "$path": "src/StarterPlayer/StarterGui/SubmarineControlGUI" }
    }
  }
}
